smart_terminal/__init__.py
smart_terminal/adapters/__init__.py
smart_terminal/adapters/ai_provider.py
smart_terminal/adapters/shell.py
smart_terminal/cli/__init__.py
smart_terminal/cli/arguments.py
smart_terminal/cli/interactive.py
smart_terminal/cli/main.py
smart_terminal/config/__init__.py
smart_terminal/config/defaults.py
smart_terminal/config/manager.py
smart_terminal/core/__init__.py
smart_terminal/core/ai.py
smart_terminal/core/base.py
smart_terminal/core/commands.py
smart_terminal/core/context.py
smart_terminal/core/shell_integration.py
smart_terminal/core/terminal.py
smart_terminal/exceptions/__init__.py
smart_terminal/exceptions/errors.py
smart_terminal/models/__init__.py
smart_terminal/models/command.py
smart_terminal/models/config.py
smart_terminal/models/context.py
smart_terminal/models/message.py
smart_terminal/utils/__init__.py
smart_terminal/utils/colors.py
smart_terminal/utils/helpers.py
smart_terminal/utils/logging.py
smart_terminal_cli-2.0.0.dist-info/LICENSE
smart_terminal_cli-2.0.0.dist-info/METADATA
smart_terminal_cli-2.0.0.dist-info/WHEEL
smart_terminal_cli-2.0.0.dist-info/entry_points.txt
smart_terminal_cli-2.0.0.dist-info/RECORD
