Metadata-Version: 2.1
Name: smart-terminal-cli
Version: 2.0.0
Summary: AI-Powered Terminal Command Generator and Executor
Home-page: https://github.com/muralianand12345/Smart-Terminal
License: MIT
Keywords: cli,terminal,ai,commands,natural-language
Author: Murali Anand
Author-email: smurali1607@gmail.com
Requires-Python: >=3.10,<4.0
Classifier: Intended Audience :: Developers
Classifier: Intended Audience :: System Administrators
Classifier: License :: OSI Approved :: MIT License
Classifier: Operating System :: OS Independent
Classifier: Programming Language :: Python :: 3
Classifier: Programming Language :: Python :: 3.10
Classifier: Programming Language :: Python :: 3.11
Classifier: Programming Language :: Python :: 3.12
Classifier: Programming Language :: Python :: 3.13
Classifier: Topic :: Terminals
Classifier: Topic :: Utilities
Requires-Dist: openai (>=1.65.2)
Requires-Dist: pydantic (>=2.10.6)
Project-URL: Documentation, https://github.com/muralianand12345/Smart-Terminal/README.md
Project-URL: Repository, https://github.com/muralianand12345/Smart-Terminal
